hey403/__init__.py
hey403/main.py
hey403/cli/__init__.py
hey403/cli/help_formater.py
hey403/cli/parser.py
hey403/network/__init__.py
hey403/network/ban_ips.py
hey403/network/dns_servers.py
hey403/services/__init__.py
hey403/services/dns_resolver.py
hey403/utils/__init__.py
hey403/utils/dns_utils.py
hey403/utils/network_utils.py
hey403/utils/table.py
hey403-1.2.0.dist-info/METADATA
hey403-1.2.0.dist-info/WHEEL
hey403-1.2.0.dist-info/entry_points.txt
hey403-1.2.0.dist-info/top_level.txt
hey403-1.2.0.dist-info/RECORD
