Metadata-Version: 2.2
Name: hey403
Version: 1.2.0
Summary: DNS accessibility testing tool for identifying 403 errors and network restrictions
Author-email: Diramid <diramidteam@gmail.com>
License: MIT License
Project-URL: Homepage, https://github.com/Diramid/hey-403-cli
Project-URL: Documentation, https://github.com/Diramid/hey-403-cli/blob/main/README.md
Project-URL: Issues, https://github.com/Diramid/hey-403-cli/issues
Keywords: dns,cli,security,403,http-testing,network-troubleshooting
Classifier: Programming Language :: Python :: 3
Classifier: Programming Language :: Python :: 3.11
Classifier: License :: OSI Approved :: MIT License
Classifier: Operating System :: OS Independent
Classifier: Development Status :: 4 - Beta
Classifier: Intended Audience :: System Administrators
Classifier: Topic :: Internet :: Name Service (DNS)
Classifier: Topic :: Security
Classifier: Topic :: Utilities
Requires-Python: >=3.10
Requires-Dist: dnspython>=2.7.0
Requires-Dist: requests>=2.32.3
Requires-Dist: rich>=13.9.4
